jupyter_react/__init__.py
jupyter_react/__main__.py
jupyter_react/__version__.py
jupyter_react/serverapplication.py
jupyter_react/handlers/__init__.py
jupyter_react/handlers/base.py
jupyter_react/handlers/config/__init__.py
jupyter_react/handlers/config/handler.py
jupyter_react/handlers/index/__init__.py
jupyter_react/handlers/index/handler.py
jupyter_react/handlers/react/__init__.py
jupyter_react/handlers/react/handlers.py
jupyter_react/static/README.md
jupyter_react/templates/index.html
jupyter_react/tests/__init__.py
jupyter_react/tests/test_handlers.py
jupyter_react-0.8.0.data/data/etc/jupyter/jupyter_notebook_config.d/jupyter_react.json
jupyter_react-0.8.0.data/data/etc/jupyter/jupyter_server_config.d/jupyter_react.json
jupyter_react-0.8.0.dist-info/METADATA
jupyter_react-0.8.0.dist-info/WHEEL
jupyter_react-0.8.0.dist-info/entry_points.txt
jupyter_react-0.8.0.dist-info/licenses/LICENSE
jupyter_react-0.8.0.dist-info/RECORD
